{
  "_class": "symbolInstance",
  "do_objectID": "5D9811DB-20FA-46B6-AADC-AFCB3BE71340",
  "exportOptions": {
    "_class": "exportOptions",
    "do_objectID": "56D765EE-87B9-4DC8-AF26-C831E983A51C",
    "exportFormats": [
    ],
    "includedLayerIds": [
    ],
    "layerOptions": 0,
    "shouldTrim": false
  },
  "frame": {
    "_class": "rect",
    "constrainProportions": false,
    "do_objectID": "979DF446-0EDA-42EF-B36A-4CD64EB35434",
    "height": 52,
    "width": 200,
    "x": 0,
    "y": 0
  },
  "horizontalSpacing": 0,
  "isFlippedHorizontal": false,
  "isFlippedVertical": false,
  "isLocked": false,
  "isVisible": true,
  "layerListExpandedType": 0,
  "name": "▢ / Solid / Default radius",
  "nameIsFixed": false,
  "overrideValues": [
    {
      "_class": "overrideValue",
      "do_objectID": "FA14D015-7335-42A9-A5CF-98D13A7A1D0E",
      "overrideName": "2936F3DC-DE5D-48E7-A918-1A1C13E42A7B_symbolID",
      "value": "7979089A-4CA3-4D5D-A68D-D4610FE90CEA"
    }
  ],
  "resizingConstraint": 63,
  "resizingType": 0,
  "rotation": 0,
  "scale": 1,
  "shouldBreakMaskChain": false,
  "style": {
    "_class": "style",
    "do_objectID": "1457043C-99BC-461D-AF55-961D77533054",
    "endDecorationType": 0,
    "miterLimit": 10,
    "startDecorationType": 0
  },
  "symbolID": "A1952A59-6790-469D-8611-21291A1C4DB7",
  "userInfo": {
    "com.animaapp.stc-sketch-plugin": {
      "kModelPropertiesKey": {
      }
    }
  },
  "verticalSpacing": 0
}