{
  "_class": "text",
  "attributedString": {
    "_class": "attributedString",
    "attributes": [
      {
        "_class": "stringAttribute",
        "attributes": {
          "MSAttributedStringColorAttribute": {
            "_class": "color",
            "alpha": 1,
            "blue": 0.5882352941,
            "green": 0.5568627451,
            "red": 0.5254901961
          },
          "MSAttributedStringFontAttribute": {
            "_class": "fontDescriptor",
            "attributes": {
              "name": "NotoSans-Bold",
              "size": 20
            }
          },
          "paragraphStyle": {
            "_class": "paragraphStyle",
            "maximumLineHeight": 28,
            "minimumLineHeight": 28
          }
        },
        "length": 7,
        "location": 0
      }
    ],
    "string": "Buttons"
  },
  "automaticallyDrawOnUnderlyingPath": false,
  "do_objectID": "9DF2DBAF-66B5-4E22-A743-7EDC448BD053",
  "dontSynchroniseWithSymbol": false,
  "exportOptions": {
    "_class": "exportOptions",
    "exportFormats": [
    ],
    "includedLayerIds": [
    ],
    "layerOptions": 0,
    "shouldTrim": false
  },
  "frame": {
    "_class": "rect",
    "constrainProportions": false,
    "height": 28,
    "width": 80,
    "x": -498,
    "y": 335
  },
  "glyphBounds": "{{1, 7}, {78, 16}}",
  "isFlippedHorizontal": false,
  "isFlippedVertical": false,
  "isLocked": false,
  "isVisible": true,
  "layerListExpandedType": 0,
  "lineSpacingBehaviour": 2,
  "name": "Buttons",
  "nameIsFixed": false,
  "resizingConstraint": 47,
  "resizingType": 0,
  "rotation": 0,
  "shouldBreakMaskChain": false,
  "style": {
    "_class": "style",
    "do_objectID": "B0A3B84C-DE4C-471E-810A-6FE5704FC018",
    "endDecorationType": 0,
    "miterLimit": 10,
    "sharedObjectID": "24943D5F-F0BC-44A6-99D9-ECAE54560034",
    "startDecorationType": 0,
    "textStyle": {
      "_class": "textStyle",
      "encodedAttributes": {
        "MSAttributedStringColorAttribute": {
          "_class": "color",
          "alpha": 1,
          "blue": 0.5882352941,
          "green": 0.5568627451,
          "red": 0.5254901961
        },
        "MSAttributedStringFontAttribute": {
          "_class": "fontDescriptor",
          "attributes": {
            "name": "NotoSans-Bold",
            "size": 20
          }
        },
        "paragraphStyle": {
          "_class": "paragraphStyle",
          "maximumLineHeight": 28,
          "minimumLineHeight": 28
        }
      },
      "verticalAlignment": 0
    }
  },
  "textBehaviour": 0,
  "userInfo": {
    "com.animaapp.stc-sketch-plugin": {
      "kModelPropertiesKey": {
        "isAutoWidth": 1
      }
    }
  }
}